[1,["2cKSFvWoJFV4S/MIZTuAvG","f9SAdPepBC5IDlkDzQFyy8","f84TxaGqNFL56Z/AWlokms@f9941","fcEJLDXUdBd6T636xyE/pu@f9941","46YY1OQT5NxoxXcF4d+WfN@6c48a","49ve5FxSpHmaN1SMR2LmLz","caRiJjuOZPO7CQm/qfsMo1@f9941","bc9r6yzMRGfooEDi8pDmz9@6c48a","c3THuxrDVLWaPUo18VlkUh@6c48a","caRiJjuOZPO7CQm/qfsMo1@6c48a","fcEJLDXUdBd6T636xyE/pu@6c48a"],["node","_textureSource","_spriteFrame","_defaultClip","root","lb_version","anim","data","_skeletonData"],["cc.SpriteFrame",["cc.Node",["_name","_layer","_active","_components","_prefab","_parent","_children","_lpos"],0,9,4,1,2,5],["cc.UITransform",["node","__prefab","_contentSize","_anchorPoint"],3,1,4,5,5],["cc.Widget",["_alignFlags","_originalWidth","_originalHeight","_top","_bottom","node","__prefab"],-2,1,4],["cc.Sprite",["_sizeMode","node","__prefab","_spriteFrame"],2,1,4,6],["cc.Prefab",["_name"],2],["cc.Node",["_name","_layer","_parent","_components","_prefab","_lpos"],1,1,12,4,5],["cc.CompPrefabInfo",["fileId"],2],["2b4fa6EqM5C/6xbxp5spXjS",["node","__prefab","anim","lb_version"],3,1,4,1,1],["cc.PrefabInfo",["fileId","instance","nestedPrefabInstanceRoots","root","asset","targetOverrides"],0,1,1,9],["cc.PrefabInfo",["fileId","instance","targetOverrides","nestedPrefabInstanceRoots","root","asset"],-1,1,1],["cc.TargetOverrideInfo",["propertyPath","targetInfo"],2,4],["cc.TargetInfo",["localID"],2],["cc.BlockInputEvents",["node","__prefab"],3,1,4],["sp.Skeleton",["defaultSkin","defaultAnimation","_premultipliedAlpha","_preCacheMode","node","__prefab","_skeletonData"],-1,1,4,6],["cc.Animation",["node","__prefab","_clips","_defaultClip"],3,1,4,3,6],["cc.Label",["_string","_actualFontSize","_fontSize","_lineHeight","node","__prefab"],-1,1,4]],[[7,0,2],[10,0,1,2,3,4,5,5],[2,0,1,2,1],[1,0,1,5,3,4,7,3],[4,0,1,2,3,2],[15,0,1,2,3,1],[3,0,1,2,5,6,4],[5,0,2],[1,0,1,6,3,4,3],[1,0,1,5,6,3,4,7,3],[1,0,1,5,3,4,3],[1,0,2,1,5,3,4,4],[6,0,1,2,3,4,5,3],[2,0,1,1],[2,0,1,2,3,1],[3,0,3,4,1,2,5,6,6],[3,0,5,6,2],[8,0,1,2,3,1],[9,0,1,2,3,4,5,4],[11,0,1,2],[12,0,2],[4,0,1,2,2],[13,0,1,1],[14,0,1,2,3,4,5,6,5],[16,0,1,2,3,4,5,5]],[[[{"name":"dotb4","rect":{"x":0,"y":0,"width":29,"height":29},"offset":{"x":0,"y":0},"originalSize":{"width":29,"height":29},"rotated":false,"capInsets":[0,0,0,0],"vertices":{"rawPosition":[-14.5,-14.5,0,14.5,-14.5,0,-14.5,14.5,0,14.5,14.5,0],"indexes":[0,1,2,2,1,3],"uv":[0,29,29,29,0,0,29,0],"nuv":[0,0,1,0,0,1,1,1],"minPos":{"x":-14.5,"y":-14.5,"z":0},"maxPos":{"x":14.5,"y":14.5,"z":0}},"packable":true,"pixelsToUnit":100,"pivot":{"x":0.5,"y":0.5},"meshType":0}],[0],0,[0],[1],[4]],[[[7,"lyGameLoading"],[8,"lyGameLoading",33554432,[-7,-8,-9,-10],[[2,-2,[0,"0cyKtiS0pC1J54/b25tEfP"],[5,768,1366]],[6,45,1155,630,-3,[0,"1fSPjA7xRGg4x/c5BiUaxi"]],[17,-6,[0,"7ewGyV3k5HLqm5dz5EprFy"],-5,-4]],[18,"638Zm+LbRAI6UTwNUrvnaB",null,null,-1,0,[[19,["btnCloseBanner"],[20,["f9ZUnrMJpKt77RR0ZFXUrS"]]]]]],[9,"loadingBg",33554432,1,[-13,-14,-15,-16,-17],[[2,-11,[0,"9ce6ltRxpDa4Xnrz6IOXKf"],[5,768,1366]],[15,45,65,-65,745,78,-12,[0,"ddHObL2yRCuKbdfYP4/j8G"]]],[1,"4222eGiO5JcZOqaTeBI8Rf",null,null,null,1,0],[1,0,-65,0]],[10,"bg",33554432,1,[[2,-18,[0,"cdVrZ6Ac9Cm6oNY7hUp7Zr"],[5,768,1366]],[21,0,-19,[0,"aeOkXZC1BHYZNHuavBkJnD"]],[22,-20,[0,"cdTnUn2qVCQooJ3l0hM4ZU"]],[6,45,768,1366,-21,[0,"48PCeAW8FHSqzPBKqKd/+L"]]],[1,"d1autDcwFDNI8trtwZ/CsO",null,null,null,1,0]],[11,"spine",false,33554432,1,[[13,-22,[0,"64ur8DHT9I56ycqEM/pVfg"]],[23,"default","zjh",false,0,-23,[0,"42YtwyZ+9P8YLyndk86J3j"],0]],[1,"071uhNoKZDz5Yt35ROH2Gu",null,null,null,1,0]],[12,"lb_version",33554432,1,[[[14,-24,[0,"c60pZbBqJEZYonp1IPsB9u"],[5,0,27.72],[0,0,0.5]],-25,[16,12,-26,[0,"26wXFFnn9MFLYUOptMisTK"]]],4,1,4],[1,"afwBL0e8VFkLFuSp0SE24V",null,null,null,1,0],[1,-384,-669.14,0]],[3,"loadingDot1",33554432,2,[[2,-27,[0,"ffeNQvqLBK9LKhIy/0XLq9"],[5,4,4]],[4,0,-28,[0,"7exNnfIyNCDYl2ajRFq/FO"],2],[5,-29,[0,"ccGbJLLLNCM67JU7xA1AHQ"],[3,4],5]],[1,"6cweTmdihAirDbQ34yj17c",null,null,null,1,0],[1,-96,0,0]],[3,"loadingDot2",33554432,2,[[2,-30,[0,"f4OyZt8JpD2pRoodGhZV3P"],[5,4,4]],[4,0,-31,[0,"e1Y7lCuYlAS44iTJ35EkJV"],6],[5,-32,[0,"09sVYqeOJNkLoKk2qEt6rx"],[7,8,9],10]],[1,"33/wvLtQxCWodvuh3tK5wW",null,null,null,1,0],[1,-32,0,0]],[3,"loadingDot3",33554432,2,[[2,-33,[0,"4anaTaXoxFc5EaLTYynNML"],[5,4,4]],[4,0,-34,[0,"cedtMUvSNOu6uKqThT4Q/S"],11],[5,-35,[0,"ccpVu6/vREnLct9ebBs35J"],[12,13],14]],[1,"66huqn45JIVKpGBYCnEe2u",null,null,null,1,0],[1,32,0,0]],[3,"loadingDot4",33554432,2,[[2,-36,[0,"77Qe9eTphEvIJhOwQHp7I3"],[5,4,4]],[4,0,-37,[0,"11TaWrKjZC5bJJXjqDUXIV"],15],[5,-38,[0,"6eJ7hRVslNcLjYEH948BdP"],[16,17,18],19]],[1,"8dWOVWDHlCF5F2xzxvIoeL",null,null,null,1,0],[1,96,0,0]],[3,"logoImg",33554432,2,[[2,-39,[0,"c5DVaIpKJB94abqBXPXH6D"],[5,213,142]],[4,0,-40,[0,"22Kq2YzT1OdZnW4DZt8jEz"],1]],[1,"9a6hTdkoVOYqL61aYUdTHE",null,null,null,1,0],[1,4.581,94,0]],[24,"",22,22,22,5,[0,"86foYBMo5LLqFML2zVU1Am"]]],0,[0,4,1,0,0,1,0,0,1,0,5,11,0,6,4,0,0,1,0,-1,3,0,-2,4,0,-3,5,0,-4,2,0,0,2,0,0,2,0,-1,10,0,-2,6,0,-3,7,0,-4,8,0,-5,9,0,0,3,0,0,3,0,0,3,0,0,3,0,0,4,0,0,4,0,0,5,0,-2,11,0,0,5,0,0,6,0,0,6,0,0,6,0,0,7,0,0,7,0,0,7,0,0,8,0,0,8,0,0,8,0,0,9,0,0,9,0,0,9,0,0,10,0,0,10,0,7,1,40],[0,0,0,0,0,0,0,0,0,0,0,0,0,0,0,0,0,0,0,0],[8,2,2,-1,-2,3,2,-1,-2,-3,3,2,-1,-2,3,2,-1,-2,-3,3],[5,6,2,0,0,0,3,0,0,1,1,2,0,0,0,3,0,0,1,1]],[[{"name":"dotb3","rect":{"x":0,"y":0,"width":21,"height":21},"offset":{"x":0,"y":0},"originalSize":{"width":21,"height":21},"rotated":false,"capInsets":[0,0,0,0],"vertices":{"rawPosition":[-10.5,-10.5,0,10.5,-10.5,0,-10.5,10.5,0,10.5,10.5,0],"indexes":[0,1,2,2,1,3],"uv":[0,21,21,21,0,0,21,0],"nuv":[0,0,1,0,0,1,1,1],"minPos":{"x":-10.5,"y":-10.5,"z":0},"maxPos":{"x":10.5,"y":10.5,"z":0}},"packable":true,"pixelsToUnit":100,"pivot":{"x":0.5,"y":0.5},"meshType":0}],[0],0,[0],[1],[7]],[[{"name":"dotb2","rect":{"x":0,"y":0,"width":12,"height":12},"offset":{"x":0,"y":0},"originalSize":{"width":12,"height":12},"rotated":false,"capInsets":[0,0,0,0],"vertices":{"rawPosition":[-6,-6,0,6,-6,0,-6,6,0,6,6,0],"indexes":[0,1,2,2,1,3],"uv":[0,12,12,12,0,0,12,0],"nuv":[0,0,1,0,0,1,1,1],"minPos":{"x":-6,"y":-6,"z":0},"maxPos":{"x":6,"y":6,"z":0}},"packable":true,"pixelsToUnit":100,"pivot":{"x":0.5,"y":0.5},"meshType":0}],[0],0,[0],[1],[8]],[[{"name":"text_kb","rect":{"x":40,"y":17,"width":213,"height":142},"offset":{"x":0,"y":3.5},"originalSize":{"width":293,"height":183},"rotated":false,"capInsets":[0,0,0,0],"vertices":{"rawPosition":[-106.5,-71,0,106.5,-71,0,-106.5,71,0,106.5,71,0],"indexes":[0,1,2,2,1,3],"uv":[40,166,253,166,40,24,253,24],"nuv":[0.13651877133105803,0.13114754098360656,0.863481228668942,0.13114754098360656,0.13651877133105803,0.907103825136612,0.863481228668942,0.907103825136612],"minPos":{"x":-106.5,"y":-71,"z":0},"maxPos":{"x":106.5,"y":71,"z":0}},"packable":true,"pixelsToUnit":100,"pivot":{"x":0.5,"y":0.5},"meshType":0}],[0],0,[0],[1],[9]],[[{"name":"dotb1","rect":{"x":0,"y":0,"width":4,"height":4},"offset":{"x":0,"y":0},"originalSize":{"width":4,"height":4},"rotated":false,"capInsets":[0,0,0,0],"vertices":{"rawPosition":[-2,-2,0,2,-2,0,-2,2,0,2,2,0],"indexes":[0,1,2,2,1,3],"uv":[0,4,4,4,0,0,4,0],"nuv":[0,0,1,0,0,1,1,1],"minPos":{"x":-2,"y":-2,"z":0},"maxPos":{"x":2,"y":2,"z":0}},"packable":true,"pixelsToUnit":100,"pivot":{"x":0.5,"y":0.5},"meshType":0}],[0],0,[0],[1],[10]]]]
